Metadata-Version: 1.0
Name: basic-matrix-algebra-vsari
Version: 0.1
Summary: matrix algebra such as addition, subtraction, multiplication,Transpose etc.
Home-page: UNKNOWN
Author: Veli Sari
Author-email: velisari@gmail.com
License: UNKNOWN
Platform: UNKNOWN
